{
  "kind": "singleType",
  "collectionName": "certification_sections",
  "info": {
    "singularName": "certification-section",
    "pluralName": "certification-sections",
    "displayName": "Certification Section",
    "description": ""
  },
  "options": {
    "draftAndPublish": true
  },
  "pluginOptions": {
    "i18n": {
      "localized": true
    }
  },
  "attributes": {
    "title": {
      "type": "string",
      "required": true,
      "pluginOptions": {
        "i18n": {
          "localized": true
        }
      }
    },
    "subtitle": {
      "type": "text",
      "pluginOptions": {
        "i18n": {
          "localized": true
        }
      }
    }
  }
}
